pkg_19544/__init__.py
pkg_19544/clean_url.py
pkg_19544/configs/constants.py
pkg_19544/configs/tlds.py
pkg_19544/helpers/__init__.py
pkg_19544/helpers/evaluate.py
pkg_19544/helpers/sanitize.py
pkg_19544/utils/__init__.py
pkg_19544/utils/err.py
pkg_19544/utils/tld.py
pkg_19544/utils/url.py
pkg_19544/utils/ver.py
pkg_19544-1.3.7.dist-info/licenses/LICENSE
pkg_19544-1.3.7.dist-info/METADATA
pkg_19544-1.3.7.dist-info/WHEEL
pkg_19544-1.3.7.dist-info/top_level.txt
pkg_19544-1.3.7.dist-info/RECORD
