Metadata-Version: 2.4
Name: pkg-19544
Version: 1.3.7
Author-email: developers <developers@tagdots.com>
Project-URL: Changelog, https://www.notavailable.com/changelog
Project-URL: Documentation, https://www.notavailable.com/doc
Project-URL: Homepage, https://www.notavailable.com
Classifier: Intended Audience :: Developers
Classifier: Programming Language :: Python :: 3 :: Only
Classifier: Programming Language :: Python :: 3.12
Classifier: Programming Language :: Python :: 3.13
Classifier: Programming Language :: Python :: 3.14
Classifier: Topic :: Software Development :: Build Tools
Requires-Python: >=3.12.10
License-File: LICENSE
Provides-Extra: local
Requires-Dist: commitizen; extra == "local"
Requires-Dist: pre-commit; extra == "local"
Provides-Extra: test
Requires-Dist: build; extra == "test"
Requires-Dist: coverage; extra == "test"
Requires-Dist: flake8; extra == "test"
Requires-Dist: isort; extra == "test"
Requires-Dist: pyscan-rs; extra == "test"
Requires-Dist: pytest; extra == "test"
Requires-Dist: twine; extra == "test"
Dynamic: license-file
